segmentation_models_trainer/__init__.py
segmentation_models_trainer/predict.py
segmentation_models_trainer/train.py
segmentation_models_trainer/callbacks_loader/__init__.py
segmentation_models_trainer/callbacks_loader/callback.py
segmentation_models_trainer/callbacks_loader/callback_factory.py
segmentation_models_trainer/callbacks_loader/custom_callbacks.py
segmentation_models_trainer/dataset_loader/__init__.py
segmentation_models_trainer/dataset_loader/dataset.py
segmentation_models_trainer/experiment_builder/__init__.py
segmentation_models_trainer/experiment_builder/experiment.py
segmentation_models_trainer/experiment_builder/loss.py
segmentation_models_trainer/experiment_builder/metric.py
segmentation_models_trainer/hyperparameter_builder/__init__.py
segmentation_models_trainer/hyperparameter_builder/hyperparameters.py
segmentation_models_trainer/hyperparameter_builder/optimizer.py
segmentation_models_trainer/model_builder/__init__.py
segmentation_models_trainer/model_builder/segmentation_model.py
segmentation_models_trainer/model_builder/custom_models/__init__.py
segmentation_models_trainer/model_builder/custom_models/deeplabv3plus.py
segmentation_models_trainer/report_builder/__init__.py
segmentation_models_trainer-0.2.dist-info/LICENSE
segmentation_models_trainer-0.2.dist-info/METADATA
segmentation_models_trainer-0.2.dist-info/WHEEL
segmentation_models_trainer-0.2.dist-info/top_level.txt
segmentation_models_trainer-0.2.dist-info/RECORD
