Metadata-Version: 2.1
Name: segmentation-models-trainer
Version: 0.2
Summary: Image segmentation models training of popular architectures.
Home-page: https://github.com/phborba/segmentation_models_trainer
Author: Philipe Borba
Author-email: philipeborba@gmail.com
License: GPL
Keywords: tensorflow keras semantic-segmentation deep learning
Platform: UNKNOWN
Classifier: Development Status :: 4 - Beta
Classifier: Intended Audience :: Developers
Classifier: Operating System :: OS Independent
Classifier: Topic :: Software Development :: Libraries :: Python Modules
Classifier: License :: OSI Approved :: GNU General Public License v2 (GPLv2)
Classifier: Programming Language :: Python
Classifier: Programming Language :: Python :: 3
Classifier: Programming Language :: Python :: Implementation :: CPython
Classifier: Programming Language :: Python :: Implementation :: PyPy
Requires-Python: >=3.6.0
Requires-Dist: tensorflow (>=2.3.0)
Requires-Dist: segmentation-models
Requires-Dist: pillow
Requires-Dist: matplotlib
Requires-Dist: numpy
Requires-Dist: dataclasses-jsonschema
Provides-Extra: tests
Requires-Dist: pytest ; extra == 'tests'
Requires-Dist: scikit-image ; extra == 'tests'
